{"cameraMode":{"drawMode":0,"name":"Shaded","section":"Shading Mode"},"sceneLighting":false,"audioPlay":false,"sceneViewState":{"m_AlwaysRefresh":false,"showFog":true,"showSkybox":false,"showFlares":true,"showImageEffects":true,"showParticleSystems":true,"showVisualEffectGraphs":true,"m_FxEnabled":true},"in2DMode":false,"pivot":{"x":-33.948299407958987,"y":3.094595432281494,"z":-3.879657745361328},"rotation":{"x":-0.32868343591690066,"y":0.050110120326280597,"z":-0.01746922917664051,"w":-0.942956805229187},"size":3.2214694023132326,"orthographic":false}